constant_properties_protector/__init__.py
constant_properties_protector/constant_properties_protector.py
constant_properties_protector-0.2.2.dist-info/LICENSE
constant_properties_protector-0.2.2.dist-info/METADATA
constant_properties_protector-0.2.2.dist-info/WHEEL
constant_properties_protector-0.2.2.dist-info/top_level.txt
constant_properties_protector-0.2.2.dist-info/RECORD
