Metadata-Version: 2.1
Name: constant-properties-protector
Version: 0.2.2
Summary: UNKNOWN
Home-page: https://github.com/BehzadShayegh/constant-properties-protector
Author: Behzad Shayegh
Author-email: behzad.shayegh@ut.ac.ir
License: UNKNOWN
Project-URL: Bug Tracker, https://github.com/BehzadShayegh/constant-properties-protector/issues
Platform: UNKNOWN
Classifier: Programming Language :: Python :: 3
Classifier: License :: OSI Approved :: MIT License
Classifier: Operating System :: OS Independent
Requires-Python: >=3.6
License-File: LICENSE
